{"frames": {

"back.png":
{
	"frame": {"x":745,"y":116,"w":126,"h":115},
	"rotated": false,
	"trimmed": false,
	"spriteSourceSize": {"x":0,"y":0,"w":126,"h":115},
	"sourceSize": {"w":126,"h":115}
},
"backDown.png":
{
	"frame": {"x":1363,"y":1,"w":126,"h":113},
	"rotated": false,
	"trimmed": false,
	"spriteSourceSize": {"x":0,"y":0,"w":126,"h":113},
	"sourceSize": {"w":126,"h":113}
},
"createRoom.png":
{
	"frame": {"x":873,"y":116,"w":232,"h":115},
	"rotated": false,
	"trimmed": false,
	"spriteSourceSize": {"x":0,"y":0,"w":232,"h":115},
	"sourceSize": {"w":232,"h":115}
},
"createRoomDown.png":
{
	"frame": {"x":1491,"y":1,"w":232,"h":113},
	"rotated": false,
	"trimmed": false,
	"spriteSourceSize": {"x":0,"y":0,"w":232,"h":113},
	"sourceSize": {"w":232,"h":113}
},
"cursor.png":
{
	"frame": {"x":1,"y":1,"w":24,"h":28},
	"rotated": false,
	"trimmed": false,
	"spriteSourceSize": {"x":0,"y":0,"w":24,"h":28},
	"sourceSize": {"w":24,"h":28}
},
"cursorClick.png":
{
	"frame": {"x":27,"y":1,"w":30,"h":28},
	"rotated": false,
	"trimmed": false,
	"spriteSourceSize": {"x":0,"y":0,"w":30,"h":28},
	"sourceSize": {"w":30,"h":28}
},
"cursorHover.png":
{
	"frame": {"x":59,"y":1,"w":29,"h":30},
	"rotated": false,
	"trimmed": false,
	"spriteSourceSize": {"x":0,"y":0,"w":29,"h":30},
	"sourceSize": {"w":29,"h":30}
},
"down.png":
{
	"frame": {"x":90,"y":1,"w":44,"h":41},
	"rotated": false,
	"trimmed": false,
	"spriteSourceSize": {"x":0,"y":0,"w":44,"h":41},
	"sourceSize": {"w":44,"h":41}
},
"easyMode.png":
{
	"frame": {"x":1393,"y":116,"w":378,"h":143},
	"rotated": false,
	"trimmed": false,
	"spriteSourceSize": {"x":0,"y":0,"w":378,"h":143},
	"sourceSize": {"w":378,"h":143}
},
"hardMode.png":
{
	"frame": {"x":1,"y":261,"w":378,"h":143},
	"rotated": false,
	"trimmed": false,
	"spriteSourceSize": {"x":0,"y":0,"w":378,"h":143},
	"sourceSize": {"w":378,"h":143}
},
"joinRoom.png":
{
	"frame": {"x":1725,"y":1,"w":230,"h":113},
	"rotated": false,
	"trimmed": false,
	"spriteSourceSize": {"x":0,"y":0,"w":230,"h":113},
	"sourceSize": {"w":230,"h":113}
},
"joinRoomDown.png":
{
	"frame": {"x":547,"y":1,"w":230,"h":111},
	"rotated": false,
	"trimmed": false,
	"spriteSourceSize": {"x":0,"y":0,"w":230,"h":111},
	"sourceSize": {"w":230,"h":111}
},
"left.png":
{
	"frame": {"x":136,"y":1,"w":44,"h":41},
	"rotated": false,
	"trimmed": false,
	"spriteSourceSize": {"x":0,"y":0,"w":44,"h":41},
	"sourceSize": {"w":44,"h":41}
},
"lobby.png":
{
	"frame": {"x":485,"y":779,"w":779,"h":559},
	"rotated": false,
	"trimmed": false,
	"spriteSourceSize": {"x":0,"y":0,"w":779,"h":559},
	"sourceSize": {"w":779,"h":559}
},
"ludiStage.png":
{
	"frame": {"x":1266,"y":779,"w":779,"h":559},
	"rotated": false,
	"trimmed": false,
	"spriteSourceSize": {"x":0,"y":0,"w":779,"h":559},
	"sourceSize": {"w":779,"h":559}
},
"mediumMode.png":
{
	"frame": {"x":381,"y":261,"w":378,"h":143},
	"rotated": false,
	"trimmed": false,
	"spriteSourceSize": {"x":0,"y":0,"w":378,"h":143},
	"sourceSize": {"w":378,"h":143}
},
"menuBackground.png":
{
	"frame": {"x":1,"y":1340,"w":779,"h":559},
	"rotated": false,
	"trimmed": false,
	"spriteSourceSize": {"x":0,"y":0,"w":779,"h":559},
	"sourceSize": {"w":779,"h":559}
},
"multiplayerButton.png":
{
	"frame": {"x":1107,"y":116,"w":284,"h":115},
	"rotated": false,
	"trimmed": false,
	"spriteSourceSize": {"x":0,"y":0,"w":284,"h":115},
	"sourceSize": {"w":284,"h":115}
},
"multiplayerButtonDown.png":
{
	"frame": {"x":1,"y":116,"w":284,"h":113},
	"rotated": false,
	"trimmed": false,
	"spriteSourceSize": {"x":0,"y":0,"w":284,"h":113},
	"sourceSize": {"w":284,"h":113}
},
"mushStage.png":
{
	"frame": {"x":782,"y":1340,"w":779,"h":559},
	"rotated": false,
	"trimmed": false,
	"spriteSourceSize": {"x":0,"y":0,"w":779,"h":559},
	"sourceSize": {"w":779,"h":559}
},
"mushStand.png":
{
	"frame": {"x":1,"y":779,"w":482,"h":534},
	"rotated": false,
	"trimmed": false,
	"spriteSourceSize": {"x":0,"y":0,"w":482,"h":534},
	"sourceSize": {"w":482,"h":534}
},
"OKButton.png":
{
	"frame": {"x":1237,"y":1,"w":124,"h":113},
	"rotated": false,
	"trimmed": false,
	"spriteSourceSize": {"x":0,"y":0,"w":124,"h":113},
	"sourceSize": {"w":124,"h":113}
},
"OKButtonDown.png":
{
	"frame": {"x":421,"y":1,"w":124,"h":111},
	"rotated": false,
	"trimmed": false,
	"spriteSourceSize": {"x":0,"y":0,"w":124,"h":111},
	"sourceSize": {"w":124,"h":111}
},
"right.png":
{
	"frame": {"x":182,"y":1,"w":44,"h":41},
	"rotated": false,
	"trimmed": false,
	"spriteSourceSize": {"x":0,"y":0,"w":44,"h":41},
	"sourceSize": {"w":44,"h":41}
},
"roomIdStand.png":
{
	"frame": {"x":1141,"y":261,"w":491,"h":516},
	"rotated": false,
	"trimmed": false,
	"spriteSourceSize": {"x":0,"y":0,"w":491,"h":516},
	"sourceSize": {"w":491,"h":516}
},
"singlePlayerButton.png":
{
	"frame": {"x":287,"y":116,"w":282,"h":113},
	"rotated": false,
	"trimmed": false,
	"spriteSourceSize": {"x":0,"y":0,"w":282,"h":113},
	"sourceSize": {"w":282,"h":113}
},
"singlePlayerButtonDown.png":
{
	"frame": {"x":779,"y":1,"w":282,"h":111},
	"rotated": false,
	"trimmed": false,
	"spriteSourceSize": {"x":0,"y":0,"w":282,"h":111},
	"sourceSize": {"w":282,"h":111}
},
"spacebar.png":
{
	"frame": {"x":228,"y":1,"w":191,"h":45},
	"rotated": false,
	"trimmed": false,
	"spriteSourceSize": {"x":0,"y":0,"w":191,"h":45},
	"sourceSize": {"w":191,"h":45}
},
"start.png":
{
	"frame": {"x":571,"y":116,"w":172,"h":113},
	"rotated": false,
	"trimmed": false,
	"spriteSourceSize": {"x":0,"y":0,"w":172,"h":113},
	"sourceSize": {"w":172,"h":113}
},
"startDown.png":
{
	"frame": {"x":1063,"y":1,"w":172,"h":111},
	"rotated": false,
	"trimmed": false,
	"spriteSourceSize": {"x":0,"y":0,"w":172,"h":111},
	"sourceSize": {"w":172,"h":111}
},
"superEasyMode.png":
{
	"frame": {"x":761,"y":261,"w":378,"h":143},
	"rotated": false,
	"trimmed": false,
	"spriteSourceSize": {"x":0,"y":0,"w":378,"h":143},
	"sourceSize": {"w":378,"h":143}
}},
"meta": {
	"app": "https://www.codeandweb.com/texturepacker",
	"version": "1.0",
	"image": "menuSheet.png",
	"format": "RGBA8888",
	"size": {"w":2046,"h":1900},
	"scale": "1",
	"smartupdate": "$TexturePacker:SmartUpdate:c83bdabde03499df2c097b75c2bd3f05:e39e18deda2ba405452a777323cc2951:9ee70c25a364bfcca3f261cfb3faa32a$"
}
}
